{"title":"북저널리즘","url":"https://www.bookjournalism.com/books","favicon":"https://www.bookjournalism.com/img/favicon.png?mtime=1592277068","elements":[{"title":"북저널리즘 라디오 에피소드 #35에선, 에듀테크 앱 ‘콴다’가 그리는 평등한 교육의 시대, 장애를 비장애로 바꾸는 에이블테크의 세계, 전 세계가 주목하고 있는 배양육 시장과 대체 단백질의 미래에 대해 이야기합니다.","contents":"기술의 진보는 격차를 좁힐 수 있을까?","link":"https://www.bookjournalism.com/audio/50711","retrieved":1652012535584},{"title":"김포국제공항에 시각 장애인용 무인 항공권 발급기가 도입됐다. 편의를 증진하는 에이블테크에선 어떤 미래를 엿볼 수 있을까.","contents":"초연결 사회의 에이블테크","link":"https://www.bookjournalism.com/books/50690","retrieved":1652012535586},{"title":"장애인에 대한 차별이 존재한다는 것은 착각입니다. 차별이 만들어 낸 장애인이 존재합니다.","contents":"지하철을 타는 장애인","link":"https://www.bookjournalism.com/books/50647","retrieved":1652012535587},{"title":"현대의 바다는 인간이 만들어내는 각종 소음이 뒤섞여 해양 생명체들을 위협하고있다. 우리는 이 사태를 해결할 수 있다. 그런데 왜 행동하지 않는가?","contents":"소음의 바다","link":"https://www.bookjournalism.com/books/50631","retrieved":1652012535593},{"title":"전 세계가 배양육 시장을 주목한다. 대체 단백질은 어떤 미래를 그리려 하나?","contents":"도축 없는 미래","link":"https://www.bookjournalism.com/books/50656","retrieved":1652012535594},{"title":"에듀테크 앱 ‘콴다’의 글로벌 가입자 수가 6000만 명을 돌파했다. 인공지능은 교육 격차를 해결할 수 있을까?","contents":"사교육 아닌 사교육","link":"https://www.bookjournalism.com/books/50623","retrieved":1652012535595},{"title":"5월 첫째 주 - 문재인 대통령은 광장이 탄생시켰습니다. 광장의 5년이었습니다.","contents":"선량한 광장","link":"https://www.bookjournalism.com/books/50609","retrieved":1652012535596},{"title":"북저널리즘 라디오 에피소드 #34에선, 프랑스 대선 결과와 유럽의 우경화 상황, 11년이 지나도록 해결되지 못한 가습기 살균제 참사, 약한 고리부터 끊어내고 있는 고물가, 그리고 토종 OTT의 미래에 대해 이야기합니다.","contents":"밥값이 치솟는 가운데 유럽은 우회전","link":"https://www.bookjournalism.com/audio/50600","retrieved":1652012535598},{"title":"S의 공포가 현실이 되고 있다. 물가는 치솟는데 월급은 그대로인 시대다. 고통의 크기는 공정하지 않다.","contents":"잔인한 S의 계절","link":"https://www.bookjournalism.com/books/50591","retrieved":1652012535599},{"title":"윤석열 정부가 토종 OTT를 키우기 위해 시동을 건다. 글로벌 시장에 막 발을 들인 토종 OTT의 미래는 밝을까?","contents":"토종 OTT 살리기 프로젝트","link":"https://www.bookjournalism.com/books/50578","retrieved":1652012535616},{"title":"미국과 중국이라는 초강대국들이 서로를 향해 돌진하고 있다. 비극을 막기 위한 방법론이 필요하다.","contents":"미·중 전쟁을 막아라","link":"https://www.bookjournalism.com/books/50569","retrieved":1652012535616},{"title":"가습기 살균제 피해자 단체가 시위에 돌입했다. 피해자가 속출했던 사건은 왜 11년째 해결되지 않았나.","contents":"해결된 적 없는 미래","link":"https://www.bookjournalism.com/books/50546","retrieved":1652012535617}]}